{
    "pools": [
        {
            "rolls": 1,
            "entries": [
                {
                    "type": "loot_table",
                    "value": "lbc:neko_set_flesh/helmet"
                },
                {
                    "type": "loot_table",
                    "value": "lbc:neko_set_flesh/chestplate"
                },
                {
                    "type": "loot_table",
                    "value": "lbc:neko_set_flesh/leggings"
                },
                {
                    "type": "loot_table",
                    "value": "lbc:neko_set_flesh/boots"
                }
            ]
        }
    ]
}