{
    "pools": [
        {
            "rolls": 12,
            "entries": [
                {
                    "type": "minecraft:loot_table",
                    "weight": 4,
                    "value": "lbc:imba/bucket_rofl"
                },
                {
                    "type": "minecraft:item",
                    "weight": 1,
                    "name": "minecraft:salmon",
                    "functions": [
                        {
                            "function": "minecraft:set_components",
                            "components": {
                                "minecraft:item_model": {
                                    "floats": [
                                        7878.0
                                    ]
                                }
                            }
                        },
                        {
                            "function": "minecraft:set_name",
                            "name": [
                                {
                                    "translate": "rofl_cod",
                                    "italic": false
                                }
                            ]
                        },
                        {
                            "function": "minecraft:set_lore",
                            "mode": "replace_all",
                            "lore": [
                                {
                                    "translate": "imba_version",
                                    "italic": false
                                }
                            ]
                        },
                        {
                            "function": "minecraft:set_custom_data",
                            "tag": "{gain_bucket:1,imba:1}"
                        }
                    ]
                },
                {
                    "type": "minecraft:item",
                    "weight": 4,
                    "name": "minecraft:salmon",
                    "functions": [
                        {
                            "function": "minecraft:set_components",
                            "components": {
                                "minecraft:item_model": {
                                    "floats": [
                                        7884.0
                                    ]
                                }
                            }
                        },
                        {
                            "function": "minecraft:set_name",
                            "name": [
                                {
                                    "translate": "rofl_lava",
                                    "italic": false
                                }
                            ]
                        },
                        {
                            "function": "minecraft:set_lore",
                            "mode": "replace_all",
                            "lore": [
                                {
                                    "translate": "imba_version",
                                    "italic": false
                                }
                            ]
                        },
                        {
                            "function": "minecraft:set_custom_data",
                            "tag": "{gain_bucket:1,imba:1,lava_bucket:1}"
                        }
                    ]
                },
                {
                    "type": "minecraft:item",
                    "weight": 4,
                    "name": "minecraft:salmon",
                    "functions": [
                        {
                            "function": "minecraft:set_components",
                            "components": {
                                "minecraft:item_model": {
                                    "floats": [
                                        7887.0
                                    ]
                                }
                            }
                        },
                        {
                            "function": "minecraft:set_name",
                            "name": [
                                {
                                    "translate": "rofl_milk",
                                    "italic": false
                                }
                            ]
                        },
                        {
                            "function": "minecraft:set_lore",
                            "mode": "replace_all",
                            "lore": [
                                {
                                    "translate": "imba_version",
                                    "italic": false
                                }
                            ]
                        },
                        {
                            "function": "minecraft:set_custom_data",
                            "tag": "{gain_bucket:1,eat_cum:1,imba:1}"
                        }
                    ]
                },
                {
                    "type": "minecraft:item",
                    "weight": 4,
                    "name": "minecraft:salmon",
                    "functions": [
                        {
                            "function": "minecraft:set_components",
                            "components": {
                                "minecraft:item_model": {
                                    "floats": [
                                        7885.0
                                    ]
                                }
                            }
                        },
                        {
                            "function": "minecraft:set_name",
                            "name": [
                                {
                                    "translate": "rofl_snow",
                                    "italic": false
                                }
                            ]
                        },
                        {
                            "function": "minecraft:set_lore",
                            "mode": "replace_all",
                            "lore": [
                                {
                                    "translate": "imba_version",
                                    "italic": false
                                }
                            ]
                        },
                        {
                            "function": "minecraft:set_custom_data",
                            "tag": "{gain_bucket:1,imba:1,snow_bucket:1}"
                        }
                    ]
                },
                {
                    "type": "minecraft:item",
                    "weight": 1,
                    "name": "minecraft:salmon",
                    "functions": [
                        {
                            "function": "minecraft:set_components",
                            "components": {
                                "minecraft:item_model": {
                                    "floats": [
                                        7882.0
                                    ]
                                }
                            }
                        },
                        {
                            "function": "minecraft:set_name",
                            "name": [
                                {
                                    "translate": "rofl_axolotl",
                                    "italic": false
                                }
                            ]
                        },
                        {
                            "function": "minecraft:set_lore",
                            "mode": "replace_all",
                            "lore": [
                                {
                                    "translate": "imba_version",
                                    "italic": false
                                }
                            ]
                        },
                        {
                            "function": "minecraft:set_custom_data",
                            "tag": "{gain_bucket:1,imba:1}"
                        }
                    ]
                },
                {
                    "type": "minecraft:item",
                    "weight": 1,
                    "name": "minecraft:salmon",
                    "functions": [
                        {
                            "function": "minecraft:set_components",
                            "components": {
                                "minecraft:item_model": {
                                    "floats": [
                                        7881.0
                                    ]
                                }
                            }
                        },
                        {
                            "function": "minecraft:set_name",
                            "name": [
                                {
                                    "translate": "rofl_pufferfish",
                                    "italic": false
                                }
                            ]
                        },
                        {
                            "function": "minecraft:set_lore",
                            "mode": "replace_all",
                            "lore": [
                                {
                                    "translate": "imba_version",
                                    "italic": false
                                }
                            ]
                        },
                        {
                            "function": "minecraft:set_custom_data",
                            "tag": "{gain_bucket:1,eat_poison:1,imba:1}"
                        }
                    ]
                },
                {
                    "type": "minecraft:item",
                    "weight": 1,
                    "name": "minecraft:salmon",
                    "functions": [
                        {
                            "function": "minecraft:set_components",
                            "components": {
                                "minecraft:item_model": {
                                    "floats": [
                                        7879.0
                                    ]
                                }
                            }
                        },
                        {
                            "function": "minecraft:set_name",
                            "name": [
                                {
                                    "translate": "rofl_salmon",
                                    "italic": false
                                }
                            ]
                        },
                        {
                            "function": "minecraft:set_lore",
                            "mode": "replace_all",
                            "lore": [
                                {
                                    "translate": "imba_version",
                                    "italic": false
                                }
                            ]
                        },
                        {
                            "function": "minecraft:set_custom_data",
                            "tag": "{gain_bucket:1,imba:1}"
                        }
                    ]
                },
                {
                    "type": "minecraft:item",
                    "weight": 1,
                    "name": "minecraft:salmon",
                    "functions": [
                        {
                            "function": "minecraft:set_components",
                            "components": {
                                "minecraft:item_model": {
                                    "floats": [
                                        7880.0
                                    ]
                                }
                            }
                        },
                        {
                            "function": "minecraft:set_name",
                            "name": [
                                {
                                    "translate": "rofl_tropical_fish",
                                    "italic": false
                                }
                            ]
                        },
                        {
                            "function": "minecraft:set_lore",
                            "mode": "replace_all",
                            "lore": [
                                {
                                    "translate": "imba_version",
                                    "italic": false
                                }
                            ]
                        },
                        {
                            "function": "minecraft:set_custom_data",
                            "tag": "{gain_bucket:1,imba:1}"
                        }
                    ]
                },
                {
                    "type": "minecraft:item",
                    "weight": 4,
                    "name": "minecraft:salmon",
                    "functions": [
                        {
                            "function": "minecraft:set_components",
                            "components": {
                                "minecraft:item_model": {
                                    "floats": [
                                        7886.0
                                    ]
                                }
                            }
                        },
                        {
                            "function": "minecraft:set_name",
                            "name": [
                                {
                                    "translate": "rofl_water",
                                    "italic": false
                                }
                            ]
                        },
                        {
                            "function": "minecraft:set_lore",
                            "mode": "replace_all",
                            "lore": [
                                {
                                    "translate": "imba_version",
                                    "italic": false
                                }
                            ]
                        },
                        {
                            "function": "minecraft:set_custom_data",
                            "tag": "{gain_bucket:1,imba:1}"
                        }
                    ]
                },
                {
                    "type": "minecraft:item",
                    "weight": 1,
                    "name": "minecraft:salmon",
                    "functions": [
                        {
                            "function": "minecraft:set_components",
                            "components": {
                                "minecraft:item_model": {
                                    "floats": [
                                        7883.0
                                    ]
                                }
                            }
                        },
                        {
                            "function": "minecraft:set_name",
                            "name": [
                                {
                                    "translate": "rofl_tadpole",
                                    "italic": false
                                }
                            ]
                        },
                        {
                            "function": "minecraft:set_lore",
                            "mode": "replace_all",
                            "lore": [
                                {
                                    "translate": "imba_version",
                                    "italic": false
                                }
                            ]
                        },
                        {
                            "function": "minecraft:set_custom_data",
                            "tag": "{gain_bucket:1,imba:1}"
                        }
                    ]
                }
            ]
        }
    ]
}