{
    "criteria": {
      "requirement": {
        "trigger": "minecraft:using_item",
        "conditions": {
          "item": {
            "items": [
              "minecraft:crossbow"
            ]
          },
          "player": [
            {
              "condition": "minecraft:inverted",
              "term": {
                "condition": "minecraft:entity_properties",
                "entity": "this",
                "predicate": {
                  "location": {
                    "dimension": "minecraft:nexus"
                  }
                }
              }
            }
          ]
        }
      }
    },
    "rewards": {
      "function": "lbc:items/crossbow_charging"
    }
  }